README.txt
setup.py
collective/__init__.py
collective.flowplayer_toolbar.egg-info/PKG-INFO
collective.flowplayer_toolbar.egg-info/SOURCES.txt
collective.flowplayer_toolbar.egg-info/dependency_links.txt
collective.flowplayer_toolbar.egg-info/entry_points.txt
collective.flowplayer_toolbar.egg-info/namespace_packages.txt
collective.flowplayer_toolbar.egg-info/not-zip-safe
collective.flowplayer_toolbar.egg-info/requires.txt
collective.flowplayer_toolbar.egg-info/top_level.txt
collective/flowplayer_toolbar/__init__.py
collective/flowplayer_toolbar/configure.zcml
collective/flowplayer_toolbar/setuphandler.py
collective/flowplayer_toolbar/tests.py
collective/flowplayer_toolbar/Extensions/install.py
collective/flowplayer_toolbar/browser/__init__.py
collective/flowplayer_toolbar/browser/configure.zcml
collective/flowplayer_toolbar/browser/controls-hulu.css
collective/flowplayer_toolbar/browser/hulu.png
collective/flowplayer_toolbar/browser/flowplayer_toolbar_js/flash_controlsbar.js
collective/flowplayer_toolbar/browser/flowplayer_toolbar_js/flowplayer.accessible-controls.js
collective/flowplayer_toolbar/browser/flowplayer_toolbar_js/flowplayer.controls-3.0.2-fixed.js
collective/flowplayer_toolbar/profiles/default/collective.flowplayer_toolbar.txt
collective/flowplayer_toolbar/profiles/default/cssregistry.xml
collective/flowplayer_toolbar/profiles/default/jsregistry.xml
collective/flowplayer_toolbar/profiles/default/metadata.xml
collective/flowplayer_toolbar/profiles/default/propertiestool.xml
collective/flowplayer_toolbar/profiles/uninstall/jsregistry.xml
docs/HISTORY.txt
docs/INSTALL.txt
docs/LICENSE.GPL
docs/LICENSE.txt