Metadata-Version: 1.0
Name: collective.flowplayer-toolbar
Version: 1.0.0
Summary: A Plone module which add an accessible Javascript controlsbar to collective.flowplayer
Home-page: http://plone.org/products/collective.flowplayer_toolbar
Author: Keul
Author-email: luca@keul.it
License: GPL
Keywords: flowplayer javascript media player accessibility video
Platform: UNKNOWN
Classifier: Development Status :: 5 - Production/Stable
Classifier: Framework :: Plone
Classifier: Programming Language :: Python
Classifier: Programming Language :: Python :: 2.4
Classifier: Programming Language :: JavaScript
Classifier: Topic :: Multimedia :: Video
